LICENSE
README.md
setup.cfg
setup.py
px_django_tree.egg-info/PKG-INFO
px_django_tree.egg-info/SOURCES.txt
px_django_tree.egg-info/dependency_links.txt
px_django_tree.egg-info/requires.txt
px_django_tree.egg-info/top_level.txt
pxd_tree/__init__.py
pxd_tree/apps.py
pxd_tree/adjacency_list/__init__.py
pxd_tree/adjacency_list/apps.py
pxd_tree/adjacency_list/const.py
pxd_tree/adjacency_list/db.py
pxd_tree/adjacency_list/models.py
pxd_tree/adjacency_list/query.py
pxd_tree/adjacency_list/migrations/0001_initial.py
pxd_tree/adjacency_list/migrations/__init__.py
pxd_tree/adjacency_list/services/__init__.py
pxd_tree/adjacency_list/services/tree_collector.py
pxd_tree/flat/__init__.py
pxd_tree/flat/models.py
pxd_tree/hierarchy/__init__.py
pxd_tree/hierarchy/const.py
pxd_tree/hierarchy/db.py
pxd_tree/hierarchy/models.py
pxd_tree/hierarchy/query.py